Workbook

Sheet Mi caso
A1: Mi caso — OrderFlow
A2: App de pedidos a restaurantes. Cálculo de cuánto cuesta correrla en AWS al mes.
A4: Asumiendo
A5: Dato | B5: Valor | C5: Cómo lo justifico
A6: Usuarios activos al mes | B6: 5000 | C6: Caso medio: app ya usada en la ciudad.
A7: Restaurantes activos | B7: 35 | C7: Para que cada negocio reciba ~30 pedidos/día (realista para un restaurante chico-medio)
A8: ¿Cuántos días al mes abre la app un usuario típico? | B8: 8 | C8: Razonamiento: pide 2 veces por semana (8 días/mes) y abre la app esos días para ver o pedir.
A9: Veces que abre la app esos días | B9: 1.5 | C9: A veces abre, ve, cierra. Y vuelve a abrir un rato después para pedir. Aprox 1.5 aperturas en promedio.
A10: % de aperturas que terminan en pedido | B10: 0.5 | C10: Si el usuario abre la app es porque tiene intención. Aprox la mitad de las aperturas terminan en compra.
A13: Concepto | B13: Cantidad | C13: De dónde sale
A14: Aperturas de la app al mes | B14: =B6*B8*B9 -> 60000 | C14: 5,000 usuarios × 8 días × 1.5 aperturas
A15: Pedidos al mes | B15: =B14*B10 -> 30000 | C15: Aperturas × 50% que convierten
A16: Pedidos por día (todo el sistema) | B16: =B15/30 -> 1000 | C16: Pedidos al mes / 30 días
A17: Pedidos por restaurante por día | B17: =B16/B7 -> 28.571429 | C17: Cada negocio recibe esto al día.

Sheet Lambda
A1: Lambda — las funciones del backend
A2: Cada vez que el usuario toca algo en la app, se ejecuta una función en el servidor. AWS me va a pedir cuántas veces se ejecuta al mes.
A4: ¿Cuántas ejecuciones al mes?
A5: Acción | B5: Veces al mes | C5: Razonamiento
A6: Login / abrir la app | B6: ='Mi caso'!B14 -> 60000 | C6: 1 por cada apertura de la app
A7: Ver el menú del restaurante | B7: ='Mi caso'!B14 -> 60000 | C7: El usuario siempre mira el menú cuando entra. 1 por apertura.
A8: Ver detalle de platos | B8: ='Mi caso'!B14*2 -> 120000 | C8: El usuario abre 2 platos antes de decidir qué pedir
A9: Crear el pedido | B9: ='Mi caso'!B15 -> 30000 | C9: 1 por cada pedido que se hace
A10: Cambios de estado del pedido | B10: ='Mi caso'!B15*4 -> 120000 | C10: Cada pedido pasa por: en cocina → listo → en camino → entregado (4 cambios)
A11: Enviar notificaciones | B11: ='Mi caso'!B15*4 -> 120000 | C11: 1 notificación por cada cambio de estado
A13: TOTAL ejecuciones al mes | B13: =SUM(B6:B11) -> 510000 | C13: campo "Number of requests"
A15: Otros datos que pide la calculadora
A16: Dato | B16: Valor | C16: Justificación
A17: Duración promedio (ms) | B17: 200 | C17: Las funciones son simples: consultan la DB y responden. Aprox 200 ms cada una.
A18: Memoria (MB) | B18: 128 | C18: El mínimo de AWS. No necesito más para funciones simples.
A20: Creo que lo mejor es subir 1 sola. 1 sola con total vs 4 sumando lo mismo. Da igual ya que tienen mismo computo. Matemticamente sera lo mismo

Sheet API Gateway
A1: API Gateway — la puerta de entrada
A2: Cada llamada de la app al backend pasa primero por aquí. AWS me va a pedir cuántas llamadas al mes.
A4: ¿Cuántas llamadas al mes?
A5: Acción | B5: Llamadas al mes | C5: Razonamiento
A6: Llamadas que vienen del usuario | B6: =Lambda!B6+Lambda!B7+Lambda!B8+Lambda!B9+Lambda!B10 -> 390000 | C6: Todo lo que hace el usuario (login, ver menú, ver platos, pedir, ver estado) pasa por aquí
A7: Las notificaciones NO cuentan | B7: 0 | C7: Las notificaciones salen del servidor hacia el usuario, no entran por API Gateway
A9: TOTAL llamadas al mes | B9: =B6+B7 -> 390000 | C9: ← ESTO va en la calculadora AWS, campo "Number of requests"
A11: Otros datos
A12: Tipo de API | B12: HTTP API | C12: Más barata que REST API y suficiente para mi caso
A13: Tamaño promedio de cada llamada (KB) | B13: 1 | C13: Mis respuestas son JSON pequeños (lista de platos, estado del pedido)

Sheet DynamoDB
A1: DynamoDB — la base de datos
A2: Donde guardo usuarios, restaurantes, menús y pedidos. AWS me pide cuántas lecturas, escrituras y cuánto espacio uso.
A4: Escrituras al mes (cuando se GUARDA algo)
A5: Acción | B5: Escrituras al mes | C5: Razonamiento
A6: Guardar un pedido nuevo | B6: ='Mi caso'!B15 -> 30000 | C6: 1 escritura por pedido
A7: Actualizar estado del pedido | B7: ='Mi caso'!B15*4 -> 120000 | C7: El pedido cambia de estado 4 veces (cocina, listo, en camino, entregado)
A8: Registros de usuarios nuevos | B8: 200 | C8: Asumo ~200 nuevos al mes (crecimiento moderado)
A10: TOTAL escrituras al mes | B10: =SUM(B6:B8) -> 150200 | C10: campo "Write requests"
A12: Lecturas al mes (cuando se CONSULTA algo)
A13: Acción | B13: Lecturas al mes | C13: Razonamiento
A14: Login (buscar al usuario) | B14: ='Mi caso'!B14 -> 60000 | C14: 1 lectura por apertura de la app
A15: Cargar el menú | B15: ='Mi caso'!B14 -> 60000 | C15: 1 lectura por apertura
A16: Ver detalle de platos | B16: ='Mi caso'!B14*2 -> 120000 | C16: 2 platos consultados por apertura
A17: Consultar estado del pedido | B17: ='Mi caso'!B15*3 -> 90000 | C17: El usuario revisa ~3 veces "¿ya llega?" entre que pide y recibe
A19: TOTAL lecturas al mes | B19: =SUM(B14:B17) -> 330000 | C19: campo "Read requests"
A21: Espacio que ocupa la base de datos
A22: Pedidos guardados (12 meses de historial) | B22: ='Mi caso'!B15*12 -> 360000 | C22: Mantengo 1 año de historial
A23: Tamaño promedio de un pedido (KB) | B23: 2 | C23: Items, totales, dirección, etc. ~2 KB
A24: Usuarios guardados | B24: ='Mi caso'!B6 -> 5000 | C24: Uno por cada usuario activo
A25: Tamaño de un usuario (KB) | B25: 1 | C25: Email, nombre, dirección, etc.
A27: TOTAL espacio (GB) | B27: =(B22*B23+B24*B25)/1000000 -> 0.725 | C27: campo "Data storage"

Sheet S3
A1: S3 — archivos estáticos e imágenes
A2: Donde guardo el frontend (la web/app) y las imágenes de los platos. AWS me pide cuánto espacio, cuántas descargas y cuánta data sale a internet.
A4: Espacio guardado
A5: Contenido | B5: Tamaño (GB) | C5: Razonamiento
A6: Frontend (web/app compilada) | B6: 0.05 | C6: Una SPA típica pesa ~50 MB con assets
A7: Imágenes de platos | B7: ='Mi caso'!B7*15*0.05/1000 -> 0.02625 | C7: 35 restaurantes × ~15 platos cada uno × 50 KB por imagen
A9: TOTAL espacio (GB) | B9: =B6+B7 -> 0.07625 | C9: campo "Storage"
A11: Descargas al mes (cuando se BAJA un archivo)
A12: Acción | B12: Descargas al mes | C12: Razonamiento
A13: Cargar la web/app | B13: ='Mi caso'!B14*5 -> 300000 | C13: Cada apertura descarga ~5 archivos (HTML, CSS, JS, fuentes)
A14: Cargar imágenes de platos | B14: ='Mi caso'!B14*15 -> 900000 | C14: El usuario ve ~15 imágenes de platos por apertura
A16: TOTAL descargas (GET) al mes | B16: =B13+B14 -> 1200000 | C16: campo "GET requests"
A18: Data que sale a internet
A19: AWS cobra extra por la data que sale hacia los usuarios ("data transfer out"). Calculo cuántos GB al mes.
A21: Tamaño promedio que descarga el usuario en una apertura (MB) | B21: 1 | C21: Frontend + ~15 imágenes de 50 KB cada una ≈ 1 MB total
A23: TOTAL data que sale (GB) | B23: ='Mi caso'!B14*B21/1000 -> 60 | C23: campo "Data transfer out"

Sheet Cognito
A1: Cognito — manejo de usuarios y login
A2: Servicio que maneja el registro, login y contraseñas de los usuarios. AWS cobra por usuario activo al mes.
A4: Lo que pide la calculadora
A5: Dato | B5: Valor | C5: Razonamiento
A6: Usuarios activos al mes (MAU) | B6: ='Mi caso'!B6 -> 5000 | C6: campo "Monthly Active Users". Mismo número que en "Mi caso".
A8: Nota: Cognito tiene un nivel gratuito de 50,000 MAU. Mi caso (5,000 usuarios) entra en ese free tier que es para siempre.

Sheet Notificaciones
A1: Notificaciones — avisos al usuario
A2: Cada vez que cambia el estado del pedido, le mando un push o email al usuario. AWS me pide cuántos envíos al mes.
A4: ¿Cuántas notificaciones al mes?
A5: Tipo | B5: Envíos al mes | C5: Razonamiento
A6: Notificaciones push (SNS) | B6: ='Mi caso'!B15*4 -> 120000 | C6: Pedidos × 4 cambios de estado (cocina, listo, en camino, entregado)
A7: Emails (solo cuando el pedido se entrega) | B7: ='Mi caso'!B15 -> 30000 | C7: Un email de confirmación por cada pedido entregado
A9: TOTAL push al mes | B9: =B6 -> 120000 | C9: ← va en la calculadora AWS → SNS → "Mobile push notifications"
A10: TOTAL emails al mes | B10: =B7 -> 30000 | C10: ← va en la calculadora AWS → SNS → "Email deliveries"

Sheet Resumen
A1: Resumen — lo que voy a poner en la calculadora AWS
A2: Estos son los números que tengo que copiar a calculator.aws en cada servicio.
A4: Servicio | B4: Dato a ingresar | C4: Valor
A5: Lambda | B5: Número de ejecuciones (requests) al mes | C5: =Lambda!B13 -> 510000
A6: Lambda | B6: Duración promedio por ejecución (ms) | C6: =Lambda!B17 -> 200
A7: Lambda | B7: Memoria asignada (MB) | C7: =Lambda!B18 -> 128
A8: API Gateway | B8: Número de llamadas (requests) al mes | C8: ='API Gateway'!B9 -> 390000
A9: API Gateway | B9: Tipo de API | C9: ='API Gateway'!B12 -> HTTP API
A10: DynamoDB | B10: Escrituras al mes (write requests) | C10: =DynamoDB!B10 -> 150200
A11: DynamoDB | B11: Lecturas al mes (read requests) | C11: =DynamoDB!B19 -> 330000
A12: DynamoDB | B12: Espacio de datos (GB) | C12: =DynamoDB!B27 -> 0.725
A13: S3 | B13: Espacio almacenado (GB) | C13: ='S3'!B9 -> 0.07625
A14: S3 | B14: Descargas (GET requests) al mes | C14: ='S3'!B16 -> 1200000
A15: S3 | B15: Data que sale a internet (GB) | C15: ='S3'!B23 -> 60
A16: Cognito | B16: Usuarios activos al mes (MAU) | C16: =Cognito!B6 -> 5000
A17: SNS (push) | B17: Notificaciones push al mes | C17: =Notificaciones!B9 -> 120000
A18: SNS (email) | B18: Emails al mes | C18: =Notificaciones!B10 -> 30000 | F18: Infra de AWS | J18: TRM HOY | K18: 3800
F19: Mensual | G19: 2.11 | H19: =G19*K18 -> 8018
A20: No se puso | F20: Anual | G20: 25.32 | H20: =G20*K18 -> 96216
A21: Falta CloudWatch + logs | B21: 4-5 dolares mas de lo que de la calculadora. Esto no representa mucho gasto | F21: Costo por pedido (30K pedidos/mes) | G21: =G19/30000 -> 7.0333333e-05 | H21: =G21*K18 -> 0.26726667
A22: EventBridge + SQS
F24: Comision Rappi
F25: Rappi cobra entre 20% y 26% del valor de cada venta a través de su plataforma.
F26: Plataforma | G26: Comisión por pedido | H26: Para 30,000 pedidos/mes
F27: Rappi (20% conservador) | G27: $6,000 COP | H27: $180,000,000 COP/mes
F28: Rappi (23% promedio) | G28: $6,900 COP | H28: $207,000,000 COP/mes
F29: Rappi (26% agresivo) | G29: $7,800 COP | H29: $234,000,000 COP/mes
F30: OrderFlow (infraestructura AWS) | G30: $0.27 COP | H30: $8,007 COP/mes
F33: Procesar 30,000 pedidos al mes en AWS cuesta $8,007 pesos colombianos (~$2 USD). Para procesar esos mismos 30,000 pedidos, Rappi se quedaría con entre $180 y $234 millones de pesos en comisiones. OrderFlow tiene un costo de infraestructura ~25,000 veces menor por pedido procesado.
